README
setup.py
tests/__init__.py
tests/test_headers.py
tests/test_lang.py
tests/test_store.py
wsgi_wovn/__init__.py
wsgi_wovn/headers.py
wsgi_wovn/lang.py
wsgi_wovn/middleware.py
wsgi_wovn/store.py
wsgi_wovn/version.py
wsgi_wovn.egg-info/PKG-INFO
wsgi_wovn.egg-info/SOURCES.txt
wsgi_wovn.egg-info/dependency_links.txt
wsgi_wovn.egg-info/top_level.txt