Metadata-Version: 1.1
Name: wsgi-wovn
Version: 0.0.3
Summary: WSGI middleware for translating application by WOVN.io. A port of wovnjava.
Home-page: https://github.com/masiuchi/wsgi-wovn
Author: Masahiro IUCHI
Author-email: masahiro.iuchi@gmail.com
License: MIT License
Keywords: wsgi middleware wovn
Platform: UNKNOWN
Classifier: Development Status :: 2 - Pre-Alpha
Classifier: Intended Audience :: Developers
Classifier: License :: OSI Approved :: MIT License
Classifier: Programming Language :: Python
Classifier: Programming Language :: Python :: 3
Classifier: Programming Language :: Python :: 3.3
Classifier: Programming Language :: Python :: 3.4
Classifier: Programming Language :: Python :: 3.5
Classifier: Programming Language :: Python :: 3.6
Classifier: Topic :: Internet :: WWW/HTTP :: WSGI
Classifier: Topic :: Internet :: WWW/HTTP :: WSGI :: Middleware
Classifier: Topic :: Software Development :: Internationalization
Classifier: Topic :: Software Development :: Localization
